bucket_command_wrapper/__init__.py
bucket_command_wrapper/bucket_command_wrapper.py
bucket_command_wrapper-0.3.1.dist-info/METADATA
bucket_command_wrapper-0.3.1.dist-info/RECORD
bucket_command_wrapper-0.3.1.dist-info/WHEEL
bucket_command_wrapper-0.3.1.dist-info/entry_points.txt
bucket_command_wrapper-0.3.1.dist-info/top_level.txt
