Metadata-Version: 2.1
Name: bucket-command-wrapper
Version: 0.3.1
Summary: Wrapper to facilitate downloading / uploading files
Home-page: https://github.com/jgolob/bucket_command_wrapper
Author: Jonathan Golob
Author-email: j-dev@golob.org
License: MIT
Platform: UNKNOWN
Requires-Dist: boto3
